{"code":"tamcro","common":"Tamaulipas Crow","st_sci":"Corvus imparatus","bl_sci":"Corvus imparatus","family":"Corvidae","order":"PASSERIFORMES","iucn":"LC","iucn_s":"LC","migration":"sedentary","habitat":"Shrubland","lifestyle":"Terrestrial","yrmodified":2020,"match_type":"exact_sci","tax_flag":false,"blup":-0.801,"rf_pct":43.4,"rf_rank":1158,"bcr_code":52,"bcr_name":"Planicie Costera Y Lomerios Humedos Del Golfo De Mexico","bc_coef":0.206,"is_bimodal":0,"seasons":{"breeding":{"st_only":["85456daffffffff","85499073fffffff","8548b443fffffff","854992a3fffffff","8549914bfffffff","8549912ffffffff","8549907bfffffff","85499123fffffff","85499383fffffff","85499c4bfffffff","854998d7fffffff","8549902bfffffff","85499163fffffff","85499167fffffff","85499153fffffff","8548b2bbfffffff","8548b4cbfffffff","8549912bfffffff","8548b2b7fffffff","854993cffffffff","854993d3fffffff","8548b287fffffff","8549939bfffffff","85499143fffffff","85499c73fffffff","85456dbbfffffff","85499387fffffff","8549932bfffffff","85499c47fffffff","854992b7fffffff","85499c57fffffff","8549913bfffffff","85456d87fffffff","8548b47bfffffff","85499a4bfffffff","85499147fffffff","8549938ffffffff","85499c77fffffff","85499c7bfffffff","85499e97fffffff","85499077fffffff","854993d7fffffff","8549902ffffffff","85499377fffffff","85499047fffffff","85499177fffffff","8549930bfffffff","85499393fffffff","8548b057fffffff","8549917bfffffff","8548b453fffffff","854993bbfffffff","85499067fffffff","854992a7fffffff","8549914ffffffff","85499373fffffff","85499063fffffff","8549904ffffffff","8549928ffffffff","854992b3fffffff","8549906bfffffff","854993b7fffffff","8549938bfffffff","8549915bfffffff","85499173fffffff","854993dbfffffff","854992bbfffffff","85499367fffffff","85456d27fffffff","85499c0bfffffff","854993c3fffffff","85499397fffffff","85499c4ffffffff","85499127fffffff","85499363fffffff","8548b05bfffffff","85499c63fffffff","85499313fffffff","854993b3fffffff","85499287fffffff","854993c7fffffff","8549906ffffffff","8548b2abfffffff","85499c6bfffffff","85499c6ffffffff"],"bl_only":["85499b9bfffffff","8548b143fffffff","8548b003fffffff","8548b52ffffffff","8548b113fffffff","8549982bfffffff","85499baffffffff","8548b023fffffff","8548b5abfffffff","8548b507fffffff","85499a0ffffffff","8548b19bfffffff","8548b52bfffffff","8548b047fffffff","85499babfffffff","85499bd7fffffff","85499b97fffffff","8548b0affffffff","8548b193fffffff","8548b02bfffffff","85499bbbfffffff","8548b15bfffffff","8548b567fffffff","8548b157fffffff","85499867fffffff","8548b00ffffffff","8548b18bfffffff","8548b1c3fffffff","8548b1c7fffffff","8548b037fffffff","85499b07fffffff","8548b073fffffff","8548b033fffffff","8548b11bfffffff","85499bc7fffffff","8548b013fffffff","85499b27fffffff","85499b17fffffff","8548b07bfffffff","85499b37fffffff","8548b56bfffffff","8548b1d7fffffff","8548b00bfffffff","8548b53bfffffff","8548b01bfffffff","8548b563fffffff","8548b077fffffff","8548a65bfffffff","8548b0c7fffffff","8548b1dbfffffff","8549986ffffffff","8548b02ffffffff","8548b56ffffffff","8548b1d3fffffff","8548b533fffffff","8548b03bfffffff","85499b83fffffff","85499b87fffffff","85499b3bfffffff","8548b0a7fffffff","8548b10bfffffff","8548b523fffffff","8548b1cffffffff","85499b93fffffff","8548b153fffffff","8548b183fffffff","8548b577fffffff","8548b007fffffff","8548b1cbfffffff","8548b027fffffff","85499b33fffffff","85499b8ffffffff","8548b017fffffff","8548b063fffffff","85499a3bfffffff"],"overlap":["8548b5d3fffffff","85499a83fffffff","8548b2b3fffffff","85499a2bfffffff","8548b4b7fffffff","8548b40ffffffff","8548b583fffffff","8548b463fffffff","85499eabfffffff","8548b0cffffffff","8549986bfffffff","8548b413fffffff","85499a8ffffffff","8548b55bfffffff","8548b477fffffff","85499333fffffff","854998c7fffffff","85499ebbfffffff","8548b4a7fffffff","85499323fffffff","85499e27fffffff","85499ed7fffffff","85499a2ffffffff","85499b47fffffff","85499b43fffffff","85499e13fffffff","8548b08bfffffff","85499a47fffffff","85499b03fffffff","8548b46ffffffff","8549987bfffffff","85499863fffffff","8549930ffffffff","8548b503fffffff","85499b23fffffff","8548b0b7fffffff","8548b5d7fffffff","85499e0bfffffff","8549931bfffffff","85499b73fffffff","85499ec3fffffff","8548b49bfffffff","85499ecffffffff","85499a0bfffffff","85499a8bfffffff","8548b41bfffffff","85499eb3fffffff","85499a53fffffff","85499e33fffffff","8548b4d3fffffff","85499b4bfffffff","85499e8ffffffff","85499b7bfffffff","85499e73fffffff","85499b0bfffffff","8549984bfffffff","8549980bfffffff","85499a6bfffffff","85499877fffffff","8548b587fffffff","85499b6ffffffff","85499b2ffffffff","85499ed3fffffff","8548b493fffffff","8549916bfffffff","85456da7fffffff","8548b4dbfffffff","854993a7fffffff","85499a9bfffffff","8548b427fffffff","8548b5dbfffffff","8548b517fffffff","8548b4affffffff","85499edbfffffff","854998c3fffffff","85499b77fffffff","8548b557fffffff","8548b51bfffffff","8548a64bfffffff","8548b573fffffff","85499ac3fffffff","8548b5a3fffffff","85499873fffffff","85499a67fffffff","8548b08ffffffff","85499e2ffffffff","85499a93fffffff","8548b043fffffff","85456db7fffffff","85499aa7fffffff","85499847fffffff","8548b42bfffffff","8548b0c3fffffff","85499e53fffffff","85499853fffffff","85499bcbfffffff","8548b597fffffff","85499bd3fffffff","854993abfffffff","85499abbfffffff","8548b5c7fffffff","85499bdbfffffff","85499a33fffffff","8548b4cffffffff","8549916ffffffff","854998d3fffffff","8548b0abfffffff","85499e7bfffffff","85499a43fffffff","85499ab3fffffff","8548b457fffffff","85499b0ffffffff","85499e5bfffffff","8548b48bfffffff","85499e4ffffffff","85499e87fffffff","85499857fffffff","8548b43bfffffff","8548b50bfffffff","85499e2bfffffff","8548b0a3fffffff","85499b5bfffffff","854569b7fffffff","85499327fffffff","8548b403fffffff","85499317fffffff","8548b59bfffffff","85499ecbfffffff","8548b4c7fffffff","85499a1bfffffff","85499a97fffffff","85499eb7fffffff","85499e9bfffffff","85456db3fffffff","85499a57fffffff","85499e67fffffff","8548b497fffffff","8548b447fffffff","8548b433fffffff","8548b04ffffffff","85499e23fffffff","85499bc3fffffff","8548b0d7fffffff","8548b4abfffffff","85499bcffffffff","85499b63fffffff","854998cffffffff","85456da3fffffff","8548b54bfffffff","8548b4a3fffffff","85499e1bfffffff","85456d97fffffff","8549981bfffffff","8548b09bfffffff","85499b67fffffff","85499e47fffffff","85499ac7fffffff","8548b04bfffffff","85499e57fffffff","8549983bfffffff","8549985bfffffff","85499e07fffffff","85499803fffffff","8548b437fffffff","8548b483fffffff","8548b58bfffffff","85499ea3fffffff","8548b473fffffff","85499b57fffffff","85499b6bfffffff","8548b5cbfffffff","85499e83fffffff","85499a87fffffff","85499a17fffffff","85499aabfffffff","85499e0ffffffff","8548b093fffffff","85499b1bfffffff","85499ad7fffffff","85499e43fffffff","85499a23fffffff","8548b4b3fffffff","8548b407fffffff","8549984ffffffff","85499307fffffff","8548b5bbfffffff","854998dbfffffff","85499ea7fffffff","85499acbfffffff","85499e6ffffffff","85499acffffffff","854993a3fffffff","85499e03fffffff","8549933bfffffff","8548b4c3fffffff","85499aaffffffff","8548b4d7fffffff","8548b417fffffff","854993affffffff","8548b57bfffffff","8548b5b3fffffff","8548b553fffffff","85499e17fffffff","8548b0b3fffffff","85456d93fffffff","8548b50ffffffff","85499a07fffffff","85499b53fffffff","85499843fffffff","85499a4ffffffff","85499e37fffffff","8548b46bfffffff","85499a73fffffff","85499e4bfffffff","85499b13fffffff","85499b2bfffffff","85499ec7fffffff","85499e77fffffff","85499a03fffffff","85499303fffffff","85499a7bfffffff","85499a6ffffffff","8548b547fffffff","85499a13fffffff","8549980ffffffff","8548b58ffffffff","8548b423fffffff","8548b5c3fffffff","85499a27fffffff","85499ad3fffffff","85499a77fffffff","8548b087fffffff","8548b0d3fffffff","8548b54ffffffff","854998cbfffffff","8548b467fffffff","85499a37fffffff","8549932ffffffff","85499ab7fffffff","85499adbfffffff","8548b4bbfffffff","8548b0bbfffffff","8548b083fffffff","8548b48ffffffff","85499b8bfffffff","8548b40bfffffff","85499e6bfffffff","85499e8bfffffff","8548b593fffffff","85499337fffffff","8548b5cffffffff","85499e63fffffff","8548b487fffffff","85499e93fffffff","854569a7fffffff","8548b513fffffff","85499a63fffffff","85499eaffffffff","85499b4ffffffff","85499e3bfffffff","8548b543fffffff","8548b42ffffffff","85499aa3fffffff","8548b097fffffff"],"st_cells":349,"bl_cells":339,"overlap_cells":264,"union_cells":424,"nonoverlap_pct":37.74},"nonbreeding":{"st_only":["85456daffffffff","85499073fffffff","8548b443fffffff","854992a3fffffff","8549914bfffffff","8549912ffffffff","8549907bfffffff","85499123fffffff","85499383fffffff","85499c4bfffffff","854998d7fffffff","8549902bfffffff","85499163fffffff","85499167fffffff","85499153fffffff","8548b2bbfffffff","8548b4cbfffffff","8549912bfffffff","854993cffffffff","854993d3fffffff","8548b287fffffff","8549939bfffffff","85499143fffffff","85499c73fffffff","85456dbbfffffff","85499387fffffff","8549932bfffffff","85499c47fffffff","854992b7fffffff","85499c57fffffff","8549913bfffffff","85456d87fffffff","8548b47bfffffff","85499a4bfffffff","85499147fffffff","8549938ffffffff","85499c77fffffff","85499c7bfffffff","85499e97fffffff","85499077fffffff","854993d7fffffff","8549902ffffffff","85499377fffffff","85499047fffffff","85499177fffffff","8549930bfffffff","85499393fffffff","8548b057fffffff","8549917bfffffff","8548b453fffffff","854993bbfffffff","85499067fffffff","854992a7fffffff","8549914ffffffff","85499373fffffff","85499063fffffff","8549904ffffffff","8549928ffffffff","854992b3fffffff","8549906bfffffff","854993b7fffffff","8549938bfffffff","8549915bfffffff","85499173fffffff","854993dbfffffff","854992bbfffffff","85499367fffffff","85456d27fffffff","85499c0bfffffff","854993c3fffffff","85499397fffffff","85499c4ffffffff","85499127fffffff","85499363fffffff","8548b05bfffffff","85499c63fffffff","85499313fffffff","854993b3fffffff","85499287fffffff","854993c7fffffff","8549906ffffffff","85499c6bfffffff","85499c6ffffffff"],"bl_only":["85499b9bfffffff","8548b52ffffffff","85499baffffffff","85499babfffffff","85499bd7fffffff","8548b3cffffffff","8548b00ffffffff","8548b3c7fffffff","8548b36bfffffff","8548b3abfffffff","8548b307fffffff","8548b1c3fffffff","8548b037fffffff","85499b07fffffff","8548b11bfffffff","85499bc7fffffff","8548b3bbfffffff","8548b363fffffff","8548b3d3fffffff","8548b353fffffff","85499b37fffffff","8548b2a3fffffff","8548b077fffffff","8548b0c7fffffff","8548b1dbfffffff","8548b02ffffffff","8548b1d3fffffff","8548b533fffffff","8548b03bfffffff","85499b3bfffffff","85499b87fffffff","8548b1cffffffff","8548b3d7fffffff","8548b183fffffff","8548b007fffffff","8548b357fffffff","8548b017fffffff","8548b063fffffff","85499a3bfffffff","8548b143fffffff","8548b377fffffff","8548b023fffffff","8548b19bfffffff","8548b52bfffffff","8548b0affffffff","8548b02bfffffff","8548b33bfffffff","8548b303fffffff","8548b567fffffff","8548b157fffffff","8548b3c3fffffff","8548b3b3fffffff","8548b18bfffffff","8548b073fffffff","85499b17fffffff","8548b3b7fffffff","8548b3a3fffffff","8548b14bfffffff","8548b56bfffffff","8548b563fffffff","8548b393fffffff","8548b2affffffff","8548b10bfffffff","8548b313fffffff","8548b147fffffff","8548b38bfffffff","8548b1cbfffffff","85499b33fffffff","8548b067fffffff","8548b113fffffff","8548b383fffffff","8548b30ffffffff","8548b507fffffff","8548b39bfffffff","8548b193fffffff","8548b397fffffff","85499bbbfffffff","85499867fffffff","8548b347fffffff","8548b2a7fffffff","8548b1c7fffffff","8548b373fffffff","8548b06ffffffff","8548b333fffffff","8548b06bfffffff","8548b00bfffffff","8548b38ffffffff","8548b01bfffffff","8549986ffffffff","8548b34ffffffff","8548b56ffffffff","85499b83fffffff","8548b317fffffff","8548b153fffffff","8548b577fffffff","8548b003fffffff","8549982bfffffff","8548b5abfffffff","8548b14ffffffff","85499a0ffffffff","8548b047fffffff","8548b387fffffff","85499b97fffffff","8548b30bfffffff","8548b15bfffffff","8548b367fffffff","8548b3cbfffffff","8548b033fffffff","8548b013fffffff","85499b27fffffff","8548b07bfffffff","8548b1d7fffffff","8548b53bfffffff","8548b3dbfffffff","8548a65bfffffff","8548b0a7fffffff","8548b523fffffff","85499b93fffffff","8548b027fffffff","85499b8ffffffff","8548b3affffffff","8548b31bfffffff"],"overlap":["8548b5d3fffffff","85499a83fffffff","8548b2b3fffffff","85499a2bfffffff","8548b4b7fffffff","8548b40ffffffff","8548b583fffffff","8548b463fffffff","85499eabfffffff","8548b0cffffffff","8549986bfffffff","8548b413fffffff","85499a8ffffffff","8548b55bfffffff","8548b477fffffff","85499333fffffff","854998c7fffffff","85499ebbfffffff","8548b4a7fffffff","85499323fffffff","85499e27fffffff","85499ed7fffffff","85499a2ffffffff","85499b47fffffff","85499b43fffffff","8549980ffffffff","85499e13fffffff","85499a47fffffff","8548b46ffffffff","85499b03fffffff","8549987bfffffff","85499863fffffff","8549930ffffffff","8548b08bfffffff","8548b503fffffff","85499b23fffffff","8548b0b7fffffff","8548b5d7fffffff","85499e0bfffffff","8549931bfffffff","85499b73fffffff","85499ec3fffffff","8548b49bfffffff","85499ecffffffff","85499a0bfffffff","85499a8bfffffff","8548b41bfffffff","85499eb3fffffff","85499a53fffffff","85499e33fffffff","8548b4d3fffffff","85499b4bfffffff","8548b2b7fffffff","85499e8ffffffff","85499b7bfffffff","85499e73fffffff","85499b0bfffffff","8549984bfffffff","8549980bfffffff","85499a6bfffffff","85499877fffffff","8548b587fffffff","85499b6ffffffff","85499b2ffffffff","85499ed3fffffff","8548b493fffffff","8549916bfffffff","85456da7fffffff","8548b4dbfffffff","854993a7fffffff","85499a9bfffffff","8548b427fffffff","8548b5dbfffffff","8548b517fffffff","8548b4affffffff","85499edbfffffff","854998c3fffffff","85499b77fffffff","8548b557fffffff","8548b51bfffffff","8548a64bfffffff","8548b573fffffff","85499ac3fffffff","8548b5a3fffffff","85499873fffffff","85499a67fffffff","8548b08ffffffff","85499e2ffffffff","85499a93fffffff","8548b043fffffff","85456db7fffffff","85499aa7fffffff","85499847fffffff","8548b42bfffffff","8548b0c3fffffff","85499e53fffffff","85499853fffffff","85499bcbfffffff","8548b597fffffff","85499bd3fffffff","854993abfffffff","85499abbfffffff","8548b5c7fffffff","85499bdbfffffff","85499a33fffffff","8548b4cffffffff","8549916ffffffff","854998d3fffffff","8548b0abfffffff","85499a43fffffff","85499e7bfffffff","85499ab3fffffff","8548b457fffffff","85499b0ffffffff","85499e5bfffffff","8548b48bfffffff","85499e4ffffffff","85499e87fffffff","85499857fffffff","8548b43bfffffff","8548b50bfffffff","85499e2bfffffff","8548b0a3fffffff","85499b5bfffffff","854569b7fffffff","85499327fffffff","8548b403fffffff","85499317fffffff","8548b59bfffffff","85499ecbfffffff","8548b4c7fffffff","85499a1bfffffff","85499a97fffffff","85499eb7fffffff","85499e9bfffffff","85456db3fffffff","85499a57fffffff","85499e67fffffff","8548b497fffffff","8548b447fffffff","8548b433fffffff","8548b04ffffffff","85499e23fffffff","85499bc3fffffff","8548b0d7fffffff","8548b4abfffffff","85499bcffffffff","85499b63fffffff","854998cffffffff","85456da3fffffff","8548b54bfffffff","8548b4a3fffffff","85499e1bfffffff","85456d97fffffff","8549981bfffffff","8548b09bfffffff","85499b67fffffff","85499e47fffffff","85499ac7fffffff","8548b04bfffffff","85499e57fffffff","8549983bfffffff","8549985bfffffff","85499e07fffffff","85499803fffffff","8548b437fffffff","8548b483fffffff","8548b58bfffffff","85499ea3fffffff","8548b473fffffff","85499b57fffffff","85499b6bfffffff","8548b5cbfffffff","85499e83fffffff","85499a87fffffff","85499a17fffffff","85499aabfffffff","85499e0ffffffff","8548b093fffffff","85499b1bfffffff","85499ad7fffffff","85499e43fffffff","85499a23fffffff","8548b4b3fffffff","8548b407fffffff","8549984ffffffff","85499307fffffff","8548b5bbfffffff","854998dbfffffff","85499ea7fffffff","85499acbfffffff","85499e6ffffffff","85499acffffffff","854993a3fffffff","85499e03fffffff","8549933bfffffff","8548b4c3fffffff","85499aaffffffff","8548b4d7fffffff","8548b417fffffff","854993affffffff","8548b57bfffffff","8548b5b3fffffff","85499e17fffffff","8548b553fffffff","8548b0b3fffffff","85456d93fffffff","8548b50ffffffff","85499a07fffffff","85499b53fffffff","85499843fffffff","85499a4ffffffff","85499e37fffffff","8548b46bfffffff","85499a73fffffff","85499e4bfffffff","85499b13fffffff","85499b2bfffffff","85499ec7fffffff","85499e77fffffff","85499a03fffffff","85499a7bfffffff","85499303fffffff","85499a6ffffffff","8548b547fffffff","85499a13fffffff","8548b58ffffffff","8548b423fffffff","8548b5c3fffffff","85499ad3fffffff","85499a27fffffff","85499a77fffffff","8548b0d3fffffff","8548b087fffffff","8548b54ffffffff","854998cbfffffff","8548b467fffffff","85499a37fffffff","8549932ffffffff","8548b2abfffffff","85499ab7fffffff","85499adbfffffff","8548b4bbfffffff","8548b0bbfffffff","8548b083fffffff","8548b48ffffffff","85499b8bfffffff","8548b40bfffffff","85499e6bfffffff","85499e8bfffffff","85499337fffffff","8548b593fffffff","8548b5cffffffff","85499e63fffffff","8548b487fffffff","85499e93fffffff","854569a7fffffff","8548b513fffffff","85499a63fffffff","85499eaffffffff","85499b4ffffffff","85499e3bfffffff","8548b543fffffff","8548b42ffffffff","85499aa3fffffff","8548b097fffffff"],"st_cells":349,"bl_cells":388,"overlap_cells":266,"union_cells":471,"nonoverlap_pct":43.52},"transition":{"st_only":[],"bl_only":[],"overlap":[],"st_cells":0,"bl_cells":0,"overlap_cells":0,"union_cells":0,"nonoverlap_pct":null}}}